bookops_worldcat/__init__.py
bookops_worldcat/__version__.py
bookops_worldcat/_session.py
bookops_worldcat/authorize.py
bookops_worldcat/errors.py
bookops_worldcat/metadata_api.py
bookops_worldcat/py.typed
bookops_worldcat/query.py
bookops_worldcat/utils.py
bookops_worldcat-1.2.0.dist-info/LICENSE
bookops_worldcat-1.2.0.dist-info/METADATA
bookops_worldcat-1.2.0.dist-info/WHEEL
bookops_worldcat-1.2.0.dist-info/RECORD
