Metadata-Version: 2.3
Name: bookops-worldcat
Version: 1.2.0
Summary: OCLC WorldCat Metadata APIs wrapper
License: MIT
Keywords: api,api-wrapper,oclc,worldcat,cataloging,bibliographic records,marcxml,holdings,library metadata,marc21
Author: Tomasz Kalata
Author-email: klingaroo@gmail.com
Requires-Python: >=3.9
Classifier: Development Status :: 5 - Production/Stable
Classifier: Intended Audience :: Developers
Classifier: Intended Audience :: Education
Classifier: Intended Audience :: Information Technology
Classifier: License :: OSI Approved :: MIT License
Classifier: Natural Language :: English
Classifier: Operating System :: OS Independent
Classifier: Programming Language :: Python :: 3
Classifier: Programming Language :: Python :: 3.9
Classifier: Programming Language :: Python :: 3.10
Classifier: Programming Language :: Python :: 3.11
Classifier: Programming Language :: Python :: 3.12
Classifier: Programming Language :: Python :: 3.13
Classifier: Topic :: Software Development :: Build Tools
Classifier: Topic :: Software Development :: Libraries :: Python Modules
Requires-Dist: requests (>=2.31,<3.0)
Requires-Dist: types-requests (>=2.31.0.20240125,<3.0.0.0)
Project-URL: Bug Tracker, https://github.com/BookOps-CAT/bookops-worldcat/issues
Project-URL: Homepage, https://bookops-cat.github.io/bookops-worldcat/
Project-URL: Repository, https://github.com/BookOps-CAT/bookops-worldcat
